pelican_cite_nice/__init__.py
pelican_cite_nice/author_year.py
pelican_cite_nice/pelican_cite.py
pelican_cite_nice-0.1.0.dist-info/LICENSE
pelican_cite_nice-0.1.0.dist-info/METADATA
pelican_cite_nice-0.1.0.dist-info/WHEEL
pelican_cite_nice-0.1.0.dist-info/top_level.txt
pelican_cite_nice-0.1.0.dist-info/RECORD
