Metadata-Version: 2.1
Name: pelican-cite-nice
Version: 0.1.0
Summary: Pelican cite plugin modified to work with nice-blog theme
Home-page: http://github.com/JWKennington/pelican-cite-nice
Author: James W. Kennington
Author-email: jameswkennington@gmail.com
License: MIT
Platform: UNKNOWN
